{
  "channel_handle": "@Yarinov_Clips2009",
  "channel_url": "https://www.youtube.com/@Yarinov_Clips2009",
  "last_updated": "2026-04-27 22:36 UTC",
  "videos": [
    {
      "id": "9pe0Y3DWIU4",
      "title": "המשחק הזה גרם לי לאבד את זה | Crab Game",
      "url": "https://www.youtube.com/watch?v=9pe0Y3DWIU4",
      "short_url": "https://www.youtube.com/shorts/9pe0Y3DWIU4",
      "thumbnail": "https://i.ytimg.com/vi/9pe0Y3DWIU4/hqdefault.jpg",
      "published": "2026-04-27T20:08:36Z",
      "duration": "55:52",
      "seconds": 3352
    },
    {
      "id": "NZTMHSPRvbQ",
      "title": "אתגרתי את קרייבון ל1V1 ברובלוקס",
      "url": "https://www.youtube.com/watch?v=NZTMHSPRvbQ",
      "short_url": "https://www.youtube.com/shorts/NZTMHSPRvbQ",
      "thumbnail": "https://i.ytimg.com/vi/NZTMHSPRvbQ/hqdefault.jpg",
      "published": "2026-04-22T08:43:34Z",
      "duration": "15:58",
      "seconds": 958
    },
    {
      "id": "VghZiWYr4ls",
      "title": "זה המשחק הכי מפגר ששיחקתי בחיים שלי",
      "url": "https://www.youtube.com/watch?v=VghZiWYr4ls",
      "short_url": "https://www.youtube.com/shorts/VghZiWYr4ls",
      "thumbnail": "https://i.ytimg.com/vi/VghZiWYr4ls/hqdefault.jpg",
      "published": "2026-04-19T13:58:21Z",
      "duration": "35:17",
      "seconds": 2117
    }
  ],
  "shorts": [
    {
      "id": "EqfTQ_y6sr0",
      "title": "בגידה בשידור חי! ירינוב נגד מרקו",
      "url": "https://www.youtube.com/shorts/EqfTQ_y6sr0",
      "short_url": "https://www.youtube.com/shorts/EqfTQ_y6sr0",
      "thumbnail": "https://i.ytimg.com/vi/EqfTQ_y6sr0/hqdefault.jpg",
      "published": "2026-04-27T20:19:38Z",
      "duration": "0:31",
      "seconds": 31
    },
    {
      "id": "EP-N1KTBq2c",
      "title": "הימור של 50/50 על ה-VIP",
      "url": "https://www.youtube.com/shorts/EP-N1KTBq2c",
      "short_url": "https://www.youtube.com/shorts/EP-N1KTBq2c",
      "thumbnail": "https://i.ytimg.com/vi/EP-N1KTBq2c/hqdefault.jpg",
      "published": "2026-04-27T20:16:23Z",
      "duration": "1:14",
      "seconds": 74
    },
    {
      "id": "1qQjq19CG0c",
      "title": "ירינוב שר?!",
      "url": "https://www.youtube.com/shorts/1qQjq19CG0c",
      "short_url": "https://www.youtube.com/shorts/1qQjq19CG0c",
      "thumbnail": "https://i.ytimg.com/vi/1qQjq19CG0c/hqdefault.jpg",
      "published": "2026-04-26T15:58:36Z",
      "duration": "0:30",
      "seconds": 30
    }
  ]
}